bus_202/__init__.py
bus_202/data/__init__.py
bus_202/data/a1.xlsx
bus_202/data/a3.xlsx
bus_202/data/ceo_comp.xlsx
bus_202/data/midterm.xlsx
bus_202/data/netflix_content.xlsx
bus_202/data/new_ceo.xlsx
bus_202/data/olympic_medals.xlsx
bus_202/data/restate.xlsx
bus_202/data/sp1500_cross_sectional.xlsx
bus_202/data/sp1500_panel.xlsx
bus_202/data/sweet_things.xlsx
bus_202/data/sweet_things_simple.xlsx
bus_202/data/world_cup_goals.xlsx
bus_202/data_visualization/__init__.py
bus_202/data_visualization/boxplot.py
bus_202/data_visualization/histogram.py
bus_202/data_visualization/scatter.py
bus_202/data_visualization/trim.py
bus_202/stats/__init__.py
bus_202/stats/ci.py
bus_202/stats/moe.py
bus_202/stats/reg.py
bus_202-2.0.dist-info/METADATA
bus_202-2.0.dist-info/WHEEL
bus_202-2.0.dist-info/top_level.txt
bus_202-2.0.dist-info/RECORD
