Metadata-Version: 2.4
Name: bus_202
Version: 2.0
Summary: BUS 202, Fundamentals of Business Analytics
Author: Justin G. Davis
Author-email: 
Keywords: business,data,analysis,education
Requires-Python: >=3.7
Requires-Dist: pandas>=1.0.0
Requires-Dist: openpyxl>=3.0.0
Requires-Dist: numpy>=1.20.0
Requires-Dist: matplotlib>=3.0.0
Requires-Dist: scipy>=1.6.0
Requires-Dist: seaborn>=0.12.0
Requires-Dist: statsmodels>=0.14.0
Requires-Dist: ipympl>=0.8.0
Dynamic: author
Dynamic: keywords
Dynamic: requires-dist
Dynamic: requires-python
Dynamic: summary
